LICENSE
MANIFEST.in
README.md
cymseed3.c
cymseed3.pxd
cymseed3.pyx
pyproject.toml
setup.py
cymseed3.egg-info/PKG-INFO
cymseed3.egg-info/SOURCES.txt
cymseed3.egg-info/dependency_links.txt
cymseed3.egg-info/not-zip-safe
cymseed3.egg-info/top_level.txt
earthscope/libmseed-3.1.3/crc32c.c
earthscope/libmseed-3.1.3/extraheaders.c
earthscope/libmseed-3.1.3/extraheaders.h
earthscope/libmseed-3.1.3/fileutils.c
earthscope/libmseed-3.1.3/genutils.c
earthscope/libmseed-3.1.3/gmtime64.c
earthscope/libmseed-3.1.3/gmtime64.h
earthscope/libmseed-3.1.3/libmseed.h
earthscope/libmseed-3.1.3/logging.c
earthscope/libmseed-3.1.3/lookup.c
earthscope/libmseed-3.1.3/mseedformat.h
earthscope/libmseed-3.1.3/msio.c
earthscope/libmseed-3.1.3/msio.h
earthscope/libmseed-3.1.3/msrutils.c
earthscope/libmseed-3.1.3/pack.c
earthscope/libmseed-3.1.3/packdata.c
earthscope/libmseed-3.1.3/packdata.h
earthscope/libmseed-3.1.3/parseutils.c
earthscope/libmseed-3.1.3/selection.c
earthscope/libmseed-3.1.3/tracelist.c
earthscope/libmseed-3.1.3/unpack.c
earthscope/libmseed-3.1.3/unpack.h
earthscope/libmseed-3.1.3/unpackdata.c
earthscope/libmseed-3.1.3/unpackdata.h
earthscope/libmseed-3.1.3/yyjson.c
earthscope/libmseed-3.1.3/yyjson.h
earthscope/libmseed-3.1.3/example/lm_pack.c
earthscope/libmseed-3.1.3/example/lm_pack_rollingbuffer.c
earthscope/libmseed-3.1.3/example/lm_pararead.c
earthscope/libmseed-3.1.3/example/lm_parse.c
earthscope/libmseed-3.1.3/example/lm_read_buffer.c
earthscope/libmseed-3.1.3/example/lm_read_recordlist.c
earthscope/libmseed-3.1.3/example/lm_read_selection.c
earthscope/libmseed-3.1.3/example/lm_sids.c
earthscope/libmseed-3.1.3/example/lm_timestr.c
earthscope/libmseed-3.1.3/example/mseedview.c
earthscope/libmseed-3.1.3/test/lm_pack.c
earthscope/libmseed-3.1.3/test/lm_pack_rollingbuffer.c
earthscope/libmseed-3.1.3/test/lm_parse.c
earthscope/libmseed-3.1.3/test/lm_read_buffer.c
earthscope/libmseed-3.1.3/test/lm_read_recordlist.c
earthscope/libmseed-3.1.3/test/lm_read_selection.c
earthscope/libmseed-3.1.3/test/lm_sids.c
earthscope/libmseed-3.1.3/test/lm_timestr.c
earthscope/libmseed-3.1.3/test/test-crc.c
