Metadata-Version: 2.4
Name: cymseed3
Version: 0.1.5
Summary: A Python package for reading and writing miniseed files using libmseed 3.
Home-page: https://github.com/shakelab/cymseed3
Author: Valerio Poggi
Author-email: Valerio Poggi <vpoggi@ogs.it>
License: GPLv3
Project-URL: Homepage, https://github.com/shakelab/cymseed3
Keywords: miniseed,libmseed,seismic,data,processing
Classifier: Programming Language :: Python :: 3
Classifier: Programming Language :: C
Classifier: License :: OSI Approved :: GNU General Public License v3 (GPLv3)
Classifier: Operating System :: OS Independent
Classifier: Development Status :: 4 - Beta
Classifier: Intended Audience :: Developers
Classifier: Intended Audience :: Science/Research
Classifier: Topic :: Software Development :: Libraries
Classifier: Topic :: Scientific/Engineering
Requires-Python: >=3.6
License-File: LICENSE
Dynamic: author
Dynamic: home-page
Dynamic: license-file
Dynamic: requires-python
